postalcodes_nepal/__init__.py
postalcodes_nepal/postalcodes.py
postalcodes_nepal/__pycache__/__init__.cpython-36.pyc
postalcodes_nepal/__pycache__/postalcodes.cpython-36.pyc
postalcodes_nepal/dataset/postalcodes.json
postalcodes_nepal-1.0.0.dist-info/LICENSE
postalcodes_nepal-1.0.0.dist-info/METADATA
postalcodes_nepal-1.0.0.dist-info/WHEEL
postalcodes_nepal-1.0.0.dist-info/top_level.txt
postalcodes_nepal-1.0.0.dist-info/RECORD
