Metadata-Version: 2.1
Name: postalcodes-nepal
Version: 1.0.0
Summary: A package for working with postal codes information of Nepal
Home-page: https://github.com/beingbiplov/postalcodes-nepal
Author: Biplov
Author-email: sharmabiplov@gmail.com
License: UNKNOWN
Project-URL: Bug Reports, https://github.com/beingbiplov/postalcodes-nepal/issues
Project-URL: Source, https://github.com/beingbiplov/postalcodes-nepal
Keywords: postalcodes Nepal zipcodes postalcodes-nepal
Platform: UNKNOWN
Classifier: Programming Language :: Python :: 3
Classifier: Programming Language :: Python :: 3.5
Classifier: Programming Language :: Python :: 3.6
Classifier: Programming Language :: Python :: 3.7
Classifier: Programming Language :: Python :: 3.8
Classifier: License :: OSI Approved :: MIT License
Classifier: Operating System :: OS Independent
